{
  "project_info": {
    "project_number": "380521322612",
    "firebase_url": "https://psikotalk-86cd2.firebaseio.com",
    "project_id": "psikotalk-86cd2",
    "storage_bucket": "psikotalk-86cd2.appspot.com"
  },
  "client": [
    {
      "client_info": {
        "mobilesdk_app_id": "1:380521322612:android:f75372813a5d2862e91921",
        "android_client_info": {
          "package_name": "com.example.firebaseauth"
        }
      },
      "oauth_client": [
        {
          "client_id": "380521322612-bbhhv4a37ih9qmp7cv1f1vrp31guc61f.apps.googleusercontent.com",
          "client_type": 1,
          "android_info": {
            "package_name": "com.example.firebaseauth",
            "certificate_hash": "309916d39d6ceb3a71cf5f28e68283d8253e5e92"
          }
        },
        {
          "client_id": "380521322612-k6kirue7688ot0m0eudhl4fndiqhf0oq.apps.googleusercontent.com",
          "client_type": 3
        }
      ],
      "api_key": [
        {
          "current_key": "AIzaSyDFzh3eB23KRhQ18bs08HFRyozuSSMVu-g"
        }
      ],
      "services": {
        "appinvite_service": {
          "other_platform_oauth_client": [
            {
              "client_id": "380521322612-k6kirue7688ot0m0eudhl4fndiqhf0oq.apps.googleusercontent.com",
              "client_type": 3
            }
          ]
        }
      }
    },
    {
      "client_info": {
        "mobilesdk_app_id": "1:380521322612:android:a5b1b832b522e78fe91921",
        "android_client_info": {
          "package_name": "com.example.psikotalk"
        }
      },
      "oauth_client": [
        {
          "client_id": "380521322612-hi8poajhe2tobcudmm5gmi2hnmcbka72.apps.googleusercontent.com",
          "client_type": 1,
          "android_info": {
            "package_name": "com.example.psikotalk",
            "certificate_hash": "9a5ad5a3e26f01832c69809c83d9634ae0a5b019"
          }
        },
        {
          "client_id": "380521322612-k6kirue7688ot0m0eudhl4fndiqhf0oq.apps.googleusercontent.com",
          "client_type": 3
        }
      ],
      "api_key": [
        {
          "current_key": "AIzaSyDFzh3eB23KRhQ18bs08HFRyozuSSMVu-g"
        }
      ],
      "services": {
        "appinvite_service": {
          "other_platform_oauth_client": [
            {
              "client_id": "380521322612-k6kirue7688ot0m0eudhl4fndiqhf0oq.apps.googleusercontent.com",
              "client_type": 3
            }
          ]
        }
      }
    },
    {
      "client_info": {
        "mobilesdk_app_id": "1:380521322612:android:8f14a840b2ab31cee91921",
        "android_client_info": {
          "package_name": "com.example.psikotalk2"
        }
      },
      "oauth_client": [
        {
          "client_id": "380521322612-k6kirue7688ot0m0eudhl4fndiqhf0oq.apps.googleusercontent.com",
          "client_type": 3
        }
      ],
      "api_key": [
        {
          "current_key": "AIzaSyDFzh3eB23KRhQ18bs08HFRyozuSSMVu-g"
        }
      ],
      "services": {
        "appinvite_service": {
          "other_platform_oauth_client": [
            {
              "client_id": "380521322612-k6kirue7688ot0m0eudhl4fndiqhf0oq.apps.googleusercontent.com",
              "client_type": 3
            }
          ]
        }
      }
    }
  ],
  "configuration_version": "1"
}